web2preview/__init__.py
web2preview/cli.py
web2preview/excepts.py
web2preview/helpers.py
web2preview/models.py
web2preview/parsers.py
web2preview/previews.py
web2preview/regex.py
web2preview/tests/__init__.py
web2preview/tests/test_fixtures.py
web2preview/tests/test_generic_preview.py
web2preview/tests/test_opengraph.py
web2preview/tests/test_preview_base.py
web2preview/tests/test_schema.py
web2preview/tests/test_twittercard.py
web2preview/tests/test_web_preview.py
web2preview/version.py
web2preview-1.1.3.dist-info/entry_points.txt
web2preview-1.1.3.dist-info/LICENSE.txt
web2preview-1.1.3.dist-info/WHEEL
web2preview-1.1.3.dist-info/METADATA
web2preview-1.1.3.dist-info/RECORD
