Metadata-Version: 2.1
Name: web2preview
Version: 1.1.3
Summary: Extracts OpenGraph, TwitterCard and Schema properties from a webpage.
Home-page: https://github.com/vduseev/web2preview
License: MIT
Keywords: preview,webpage,opengraph,twittercard,schema
Author: vduseev
Author-email: vagiz@duseev.com
Maintainer: vduseev
Maintainer-email: vagiz@duseev.com
Requires-Python: >=3.7,<4.0
Classifier: License :: OSI Approved :: MIT License
Classifier: Programming Language :: Python :: 3
Classifier: Programming Language :: Python :: 3.10
Classifier: Programming Language :: Python :: 3.7
Classifier: Programming Language :: Python :: 3.8
Classifier: Programming Language :: Python :: 3.9
Requires-Dist: beautifulsoup4 (>=4.0,<5.0)
Requires-Dist: requests (>=2.0,<3.0)
Project-URL: Documentation, https://github.com/vduseev/web2preview
Project-URL: Repository, https://github.com/vduseev/web2preview
